Workbook
Name Average_Sales: Sales_Dashboard!$K$5
Name Profit: Sales_Dashboard!$N$5
Name Slicer_Category: #N/A
Name Slicer_Region: #N/A
Name Total_Order: Sales_Dashboard!$H$5
Name Total_Sales: Sales_Dashboard!$F$5

Sheet Sales
A1: Sales_id | B1: Product_id | C1: Category | D1: Customer_id | E1: Customer_name | F1: Date | G1: Quantity_sold | H1: Cost_price | I1: Unit_Price | J1: Total_amount | K1: Payment_method | L1: Sales_rep | M1: Region | N1: Profit
A2: SAL001 | B2: P083 | C2: =_xlfn.XLOOKUP(tblSales[[#This Row],[Product_id]],Products!A:A,Products!C:C) -> Agricultural Equipment | D2: CUST176 | E2: Funmilayo Akintola | F2: 45670 | G2: 5 | H2: =_xlfn.XLOOKUP(tblSales[[#This Row],[Product_id]],Products!A:A,Products!E:E) -> 8500 | I2: =_xlfn.XLOOKUP(tblSales[[#This Row],[Product_id]],Products!A:A,Products!F:F) -> 15000 | J2: =tblSales[[#This Row],[Quantity_sold]]*tblSales[[#This Row],[Unit_Price]] -> 75000 | K2: Transfer | L2: Sadiq Bello | M2: Ibadan | N2: =tblSales[[#This Row],[Unit_Price]]*tblSales[[#This Row],[Quantity_sold]]-tblSales[[#This Row],[Cost_price]]*tblSales[[#This Row],[Quantity_sold]] -> 32500
A3: SAL002 | B3: P008 | C3: =_xlfn.XLOOKUP(tblSales[[#This Row],[Product_id]],Products!A:A,Products!C:C) -> Agricultural Equipment | D3: CUST022 | E3: Aminat Hassan | F3: 45663 | G3: 3 | H3: =_xlfn.XLOOKUP(tblSales[[#This Row],[Product_id]],Products!A:A,Products!E:E) -> 15000 | I3: =_xlfn.XLOOKUP(tblSales[[#This Row],[Product_id]],Products!A:A,Products!F:F) -> 24000 | J3: =tblSales[[#This Row],[Quantity_sold]]*tblSales[[#This Row],[Unit_Price]] -> 72000 | K3: POS | L3: Segun Ajayi | M3: Ibadan | N3: =tblSales[[#This Row],[Unit_Price]]*tblSales[[#This Row],[Quantity_sold]]-tblSales[[#This Row],[Cost_price]]*tblSales[[#This Row],[Quantity_sold]] -> 27000
A4: SAL003 | B4: P001 | C4: =_xlfn.XLOOKUP(tblSales[[#This Row],[Product_id]],Products!A:A,Products!C:C) -> Agricultural Machine | D4: CUST079 | E4: Blessing Egwu | F4: 45673 | G4: 14 | H4: =_xlfn.XLOOKUP(tblSales[[#This Row],[Product_id]],Products!A:A,Products!E:E) -> 120000 | I4: =_xlfn.XLOOKUP(tblSales[[#This Row],[Product_id]],Products!A:A,Products!F:F) -> 165000 | J4: =tblSales[[#This Row],[Quantity_sold]]*tblSales[[#This Row],[Unit_Price]] -> 2310000 | K4: Cash | L4: Fatima Abdullahi | M4: Enugu | N4: =tblSales[[#This Row],[Unit_Price]]*tblSales[[#This Row],[Quantity_sold]]-tblSales[[#This Row],[Cost_price]]*tblSales[[#This Row],[Quantity_sold]] -> 630000
A5: SAL004 | B5: P022 | C5: =_xlfn.XLOOKUP(tblSales[[#This Row],[Product_id]],Products!A:A,Products!C:C) -> Agricultural Equipment | D5: CUST198 | E5: Kudirat Ahmed | F5: 45663 | G5: 12 | H5: =_xlfn.XLOOKUP(tblSales[[#This Row],[Product_id]],Products!A:A,Products!E:E) -> 32000 | I5: =_xlfn.XLOOKUP(tblSales[[#This Row],[Product_id]],Products!A:A,Products!F:F) -> 48000 | J5: =tblSales[[#This Row],[Quantity_sold]]*tblSales[[#This Row],[Unit_Price]] -> 576000 | K5: Transfer | L5: Segun Ajayi | M5: Kano | N5: =tblSales[[#This Row],[Unit_Price]]*tblSales[[#This Row],[Quantity_sold]]-tblSales[[#This Row],[Cost_price]]*tblSales[[#This Row],[Quantity_sold]] -> 192000
A6: SAL005 | B6: P054 | C6: =_xlfn.XLOOKUP(tblSales[[#This Row],[Product_id]],Products!A:A,Products!C:C) -> Safety Equipment | D6: CUST051 | E6: Halima Abubakar | F6: 45685 | G6: 10 | H6: =_xlfn.XLOOKUP(tblSales[[#This Row],[Product_id]],Products!A:A,Products!E:E) -> 35000 | I6: =_xlfn.XLOOKUP(tblSales[[#This Row],[Product_id]],Products!A:A,Products!F:F) -> 55000 | J6: =tblSales[[#This Row],[Quantity_sold]]*tblSales[[#This Row],[Unit_Price]] -> 550000 | K6: POS | L6: Ebele Okoro | M6: Kaduna | N6: =tblSales[[#This Row],[Unit_Price]]*tblSales[[#This Row],[Quantity_sold]]-tblSales[[#This Row],[Cost_price]]*tblSales[[#This Row],[Quantity_sold]] -> 200000
A7: SAL006 | B7: P041 | C7: =_xlfn.XLOOKUP(tblSales[[#This Row],[Product_id]],Products!A:A,Products!C:C) -> Agricultural Machine | D7: CUST228 | E7: Joyce Akpan | F7: 45658 | G7: 17 | H7: =_xlfn.XLOOKUP(tblSales[[#This Row],[Product_id]],Products!A:A,Products!E:E) -> 155000 | I7: =_xlfn.XLOOKUP(tblSales[[#This Row],[Product_id]],Products!A:A,Products!F:F) -> 215000 | J7: =tblSales[[#This Row],[Quantity_sold]]*tblSales[[#This Row],[Unit_Price]] -> 3655000 | K7: Cash | L7: Sadiq Bello | M7: Portharcourt | N7: =tblSales[[#This Row],[Unit_Price]]*tblSales[[#This Row],[Quantity_sold]]-tblSales[[#This Row],[Cost_price]]*tblSales[[#This Row],[Quantity_sold]] -> 1020000
A8: SAL007 | B8: P022 | C8: =_xlfn.XLOOKUP(tblSales[[#This Row],[Product_id]],Products!A:A,Products!C:C) -> Agricultural Equipment | D8: CUST217 | E8: Lawrence Okoro | F8: 45681 | G8: 17 | H8: =_xlfn.XLOOKUP(tblSales[[#This Row],[Product_id]],Products!A:A,Products!E:E) -> 32000 | I8: =_xlfn.XLOOKUP(tblSales[[#This Row],[Product_id]],Products!A:A,Products!F:F) -> 48000 | J8: =tblSales[[#This Row],[Quantity_sold]]*tblSales[[#This Row],[Unit_Price]] -> 816000 | K8: Cash | L8: Fatima Abdullahi | M8: Portharcourt | N8: =tblSales[[#This Row],[Unit_Price]]*tblSales[[#This Row],[Quantity_sold]]-tblSales[[#This Row],[Cost_price]]*tblSales[[#This Row],[Quantity_sold]] -> 272000
A9: SAL008 | B9: P088 | C9: =_xlfn.XLOOKUP(tblSales[[#This Row],[Product_id]],Products!A:A,Products!C:C) -> Processing Equipment | D9: CUST247 | E9: Esther Peter | F9: 45664 | G9: 6 | H9: =_xlfn.XLOOKUP(tblSales[[#This Row],[Product_id]],Products!A:A,Products!E:E) -> 275000 | I9: =_xlfn.XLOOKUP(tblSales[[#This Row],[Product_id]],Products!A:A,Products!F:F) -> 385000 | J9: =tblSales[[#This Row],[Quantity_sold]]*tblSales[[#This Row],[Unit_Price]] -> 2310000 | K9: Transfer | L9: Sadiq Bello | M9: Lagos | N9: =tblSales[[#This Row],[Unit_Price]]*tblSales[[#This Row],[Quantity_sold]]-tblSales[[#This Row],[Cost_price]]*tblSales[[#This Row],[Quantity_sold]] -> 660000
A10: SAL009 | B10: P049 | C10: =_xlfn.XLOOKUP(tblSales[[#This Row],[Product_id]],Products!A:A,Products!C:C) -> Storage Equipment | D10: CUST042 | E10: Ahmed Ibrahim | F10: 45688 | G10: 20 | H10: =_xlfn.XLOOKUP(tblSales[[#This Row],[Product_id]],Products!A:A,Products!E:E) -> 340000 | I10: =_xlfn.XLOOKUP(tblSales[[#This Row],[Product_id]],Products!A:A,Products!F:F) -> 465000 | J10: =tblSales[[#This Row],[Quantity_sold]]*tblSales[[#This Row],[Unit_Price]] -> 9300000 | K10: POS | L10: Olufemi Adewale | M10: Ibadan | N10: =tblSales[[#This Row],[Unit_Price]]*tblSales[[#This Row],[Quantity_sold]]-tblSales[[#This Row],[Cost_price]]*tblSales[[#This Row],[Quantity_sold]] -> 2500000
A11: SAL010 | B11: P097 | C11: =_xlfn.XLOOKUP(tblSales[[#This Row],[Product_id]],Products!A:A,Products!C:C) -> Harvesting Equipment | D11: CUST187 | E11: Suleiman Ahmed | F11: 45677 | G11: 14 | H11: =_xlfn.XLOOKUP(tblSales[[#This Row],[Product_id]],Products!A:A,Products!E:E) -> 220000 | I11: =_xlfn.XLOOKUP(tblSales[[#This Row],[Product_id]],Products!A:A,Products!F:F) -> 310000 | J11: =tblSales[[#This Row],[Quantity_sold]]*tblSales[[#This Row],[Unit_Price]] -> 4340000 | K11: Cash | L11: Fatima Abdullahi | M11: Enugu | N11: =tblSales[[#This Row],[Unit_Price]]*tblSales[[#This Row],[Quantity_sold]]-tblSales[[#This Row],[Cost_price]]*tblSales[[#This Row],[Quantity_sold]] -> 1260000
A12: SAL011 | B12: P043 | C12: =_xlfn.XLOOKUP(tblSales[[#This Row],[Product_id]],Products!A:A,Products!C:C) -> Agricultural Machine | D12: CUST196 | E12: Habibat Bello | F12: 45663 | G12: 15 | H12: =_xlfn.XLOOKUP(tblSales[[#This Row],[Product_id]],Products!A:A,Products!E:E) -> 115000 | I12: =_xlfn.XLOOKUP(tblSales[[#This Row],[Product_id]],Products!A:A,Products!F:F) -> 165000 | J12: =tblSales[[#This Row],[Quantity_sold]]*tblSales[[#This Row],[Unit_Price]] -> 2475000 | K12: Transfer | L12: Olufemi Adewale | M12: Kano | N12: =tblSales[[#This Row],[Unit_Price]]*tblSales[[#This Row],[Quantity_sold]]-tblSales[[#This Row],[Cost_price]]*tblSales[[#This Row],[Quantity_sold]] -> 750000
A13: SAL012 | B13: P037 | C13: =_xlfn.XLOOKUP(tblSales[[#This Row],[Product_id]],Products!A:A,Products!C:C) -> Agricultural Machine | D13: CUST231 | E13: Blessing Nwachukwu | F13: 45687 | G13: 4 | H13: =_xlfn.XLOOKUP(tblSales[[#This Row],[Product_id]],Products!A:A,Products!E:E) -> 620000 | I13: =_xlfn.XLOOKUP(tblSales[[#This Row],[Product_id]],Products!A:A,Products!F:F) -> 820000 | J13: =tblSales[[#This Row],[Quantity_sold]]*tblSales[[#This Row],[Unit_Price]] -> 3280000 | K13: Cash | L13: Ebele Okoro | M13: Enugu | N13: =tblSales[[#This Row],[Unit_Price]]*tblSales[[#This Row],[Quantity_sold]]-tblSales[[#This Row],[Cost_price]]*tblSales[[#This Row],[Quantity_sold]] -> 800000
... A49: SAL048 | B49: P017 | C49: =_xlfn.XLOOKUP(tblSales[[#This Row],[Product_id]],Products!A:A,Products!C:C) -> Agricultural Machine | D49: CUST173 | E49: Nkiru Obi | F49: 45731 | G49: 8 | H49: =_xlfn.XLOOKUP(tblSales[[#This Row],[Product_id]],Products!A:A,Products!E:E) -> 680000 | I49: =_xlfn.XLOOKUP(tblSales[[#This Row],[Product_id]],Products!A:A,Products!F:F) -> 890000 | J49: =tblSales[[#This Row],[Quantity_sold]]*tblSales[[#This Row],[Unit_Price]] -> 7120000 | K49: POS | L49: Olufemi Adewale | M49: Kaduna | N49: =tblSales[[#This Row],[Unit_Price]]*tblSales[[#This Row],[Quantity_sold]]-tblSales[[#This Row],[Cost_price]]*tblSales[[#This Row],[Quantity_sold]] -> 1680000
A50: SAL049 | B50: P094 | C50: =_xlfn.XLOOKUP(tblSales[[#This Row],[Product_id]],Products!A:A,Products!C:C) -> Agricultural Equipment | D50: CUST044 | E50: Sarah Chima | F50: 45745 | G50: 11 | H50: =_xlfn.XLOOKUP(tblSales[[#This Row],[Product_id]],Products!A:A,Products!E:E) -> 42000 | I50: =_xlfn.XLOOKUP(tblSales[[#This Row],[Product_id]],Products!A:A,Products!F:F) -> 68000 | J50: =tblSales[[#This Row],[Quantity_sold]]*tblSales[[#This Row],[Unit_Price]] -> 748000 | K50: =CHOOSE(RANDBETWEEN(1,3), "Cash", "Transfer", "POS") -> Transfer | L50: Fatima Abdullahi | M50: Lagos | N50: =tblSales[[#This Row],[Unit_Price]]*tblSales[[#This Row],[Quantity_sold]]-tblSales[[#This Row],[Cost_price]]*tblSales[[#This Row],[Quantity_sold]] -> 286000
A51: SAL050 | B51: P061 | C51: =_xlfn.XLOOKUP(tblSales[[#This Row],[Product_id]],Products!A:A,Products!C:C) -> Agricultural Equipment | D51: CUST001 | E51: Chinedu Okafor | F51: 45741 | G51: 18 | H51: =_xlfn.XLOOKUP(tblSales[[#This Row],[Product_id]],Products!A:A,Products!E:E) -> 18500 | I51: =_xlfn.XLOOKUP(tblSales[[#This Row],[Product_id]],Products!A:A,Products!F:F) -> 29500 | J51: =tblSales[[#This Row],[Quantity_sold]]*tblSales[[#This Row],[Unit_Price]] -> 531000 | K51: =CHOOSE(RANDBETWEEN(1,3), "Cash", "Transfer", "POS") -> Transfer | L51: Olufemi Adewale | M51: Portharcourt | N51: =tblSales[[#This Row],[Unit_Price]]*tblSales[[#This Row],[Quantity_sold]]-tblSales[[#This Row],[Cost_price]]*tblSales[[#This Row],[Quantity_sold]] -> 198000
A52: SAL051 | B52: P084 | C52: =_xlfn.XLOOKUP(tblSales[[#This Row],[Product_id]],Products!A:A,Products!C:C) -> Power Equipment | D52: CUST219 | E52: Umar Mohammed | F52: 45724 | G52: 1 | H52: =_xlfn.XLOOKUP(tblSales[[#This Row],[Product_id]],Products!A:A,Products!E:E) -> 29000 | I52: =_xlfn.XLOOKUP(tblSales[[#This Row],[Product_id]],Products!A:A,Products!F:F) -> 46000 | J52: =tblSales[[#This Row],[Quantity_sold]]*tblSales[[#This Row],[Unit_Price]] -> 46000 | K52: =CHOOSE(RANDBETWEEN(1,3), "Cash", "Transfer", "POS") -> Transfer | L52: Amara Nwosu | M52: Kano | N52: =tblSales[[#This Row],[Unit_Price]]*tblSales[[#This Row],[Quantity_sold]]-tblSales[[#This Row],[Cost_price]]*tblSales[[#This Row],[Quantity_sold]] -> 17000
A53: SAL052 | B53: P025 | C53: =_xlfn.XLOOKUP(tblSales[[#This Row],[Product_id]],Products!A:A,Products!C:C) -> Storage Equipment | D53: CUST243 | E53: Patience Nwankwo | F53: 45775 | G53: 10 | H53: =_xlfn.XLOOKUP(tblSales[[#This Row],[Product_id]],Products!A:A,Products!E:E) -> 510000 | I53: =_xlfn.XLOOKUP(tblSales[[#This Row],[Product_id]],Products!A:A,Products!F:F) -> 690000 | J53: =tblSales[[#This Row],[Quantity_sold]]*tblSales[[#This Row],[Unit_Price]] -> 6900000 | K53: =CHOOSE(RANDBETWEEN(1,3), "Cash", "Transfer", "POS") -> Cash | L53: Sadiq Bello | M53: Kaduna | N53: =tblSales[[#This Row],[Unit_Price]]*tblSales[[#This Row],[Quantity_sold]]-tblSales[[#This Row],[Cost_price]]*tblSales[[#This Row],[Quantity_sold]] -> 1800000
A54: SAL053 | B54: P047 | C54: =_xlfn.XLOOKUP(tblSales[[#This Row],[Product_id]],Products!A:A,Products!C:C) -> Agricultural Equipment | D54: CUST219 | E54: Umar Mohammed | F54: 45772 | G54: 3 | H54: =_xlfn.XLOOKUP(tblSales[[#This Row],[Product_id]],Products!A:A,Products!E:E) -> 165000 | I54: =_xlfn.XLOOKUP(tblSales[[#This Row],[Product_id]],Products!A:A,Products!F:F) -> 230000 | J54: =tblSales[[#This Row],[Quantity_sold]]*tblSales[[#This Row],[Unit_Price]] -> 690000 | K54: =CHOOSE(RANDBETWEEN(1,3), "Cash", "Transfer", "POS") -> Transfer | L54: Fatima Abdullahi | M54: Ibadan | N54: =tblSales[[#This Row],[Unit_Price]]*tblSales[[#This Row],[Quantity_sold]]-tblSales[[#This Row],[Cost_price]]*tblSales[[#This Row],[Quantity_sold]] -> 195000
A55: SAL054 | B55: P017 | C55: =_xlfn.XLOOKUP(tblSales[[#This Row],[Product_id]],Products!A:A,Products!C:C) -> Agricultural Machine | D55: CUST042 | E55: Ahmed Ibrahim | F55: 45763 | G55: 4 | H55: =_xlfn.XLOOKUP(tblSales[[#This Row],[Product_id]],Products!A:A,Products!E:E) -> 680000 | I55: =_xlfn.XLOOKUP(tblSales[[#This Row],[Product_id]],Products!A:A,Products!F:F) -> 890000 | J55: =tblSales[[#This Row],[Quantity_sold]]*tblSales[[#This Row],[Unit_Price]] -> 3560000 | K55: =CHOOSE(RANDBETWEEN(1,3), "Cash", "Transfer", "POS") -> POS | L55: Sadiq Bello | M55: Enugu | N55: =tblSales[[#This Row],[Unit_Price]]*tblSales[[#This Row],[Quantity_sold]]-tblSales[[#This Row],[Cost_price]]*tblSales[[#This Row],[Quantity_sold]] -> 840000
A56: SAL055 | B56: P072 | C56: =_xlfn.XLOOKUP(tblSales[[#This Row],[Product_id]],Products!A:A,Products!C:C) -> Agricultural Equipment | D56: CUST176 | E56: Funmilayo Akintola | F56: 45765 | G56: 7 | H56: =_xlfn.XLOOKUP(tblSales[[#This Row],[Product_id]],Products!A:A,Products!E:E) -> 56000 | I56: =_xlfn.XLOOKUP(tblSales[[#This Row],[Product_id]],Products!A:A,Products!F:F) -> 85000 | J56: =tblSales[[#This Row],[Quantity_sold]]*tblSales[[#This Row],[Unit_Price]] -> 595000 | K56: =CHOOSE(RANDBETWEEN(1,3), "Cash", "Transfer", "POS") -> Transfer | L56: Ebele Okoro | M56: Enugu | N56: =tblSales[[#This Row],[Unit_Price]]*tblSales[[#This Row],[Quantity_sold]]-tblSales[[#This Row],[Cost_price]]*tblSales[[#This Row],[Quantity_sold]] -> 203000
A57: SAL056 | B57: P023 | C57: =_xlfn.XLOOKUP(tblSales[[#This Row],[Product_id]],Products!A:A,Products!C:C) -> Processing Equipment | D57: CUST097 | E57: Obinna Nwosu | F57: 45753 | G57: 16 | H57: =_xlfn.XLOOKUP(tblSales[[#This Row],[Product_id]],Products!A:A,Products!E:E) -> 360000 | I57: =_xlfn.XLOOKUP(tblSales[[#This Row],[Product_id]],Products!A:A,Products!F:F) -> 480000 | J57: =tblSales[[#This Row],[Quantity_sold]]*tblSales[[#This Row],[Unit_Price]] -> 7680000 | K57: =CHOOSE(RANDBETWEEN(1,3), "Cash", "Transfer", "POS") -> Transfer | L57: Fatima Abdullahi | M57: Lagos | N57: =tblSales[[#This Row],[Unit_Price]]*tblSales[[#This Row],[Quantity_sold]]-tblSales[[#This Row],[Cost_price]]*tblSales[[#This Row],[Quantity_sold]] -> 1920000
A58: SAL057 | B58: P025 | C58: =_xlfn.XLOOKUP(tblSales[[#This Row],[Product_id]],Products!A:A,Products!C:C) -> Storage Equipment | D58: CUST240 | E58: Felix Johnson | F58: 45776 | G58: 4 | H58: =_xlfn.XLOOKUP(tblSales[[#This Row],[Product_id]],Products!A:A,Products!E:E) -> 510000 | I58: =_xlfn.XLOOKUP(tblSales[[#This Row],[Product_id]],Products!A:A,Products!F:F) -> 690000 | J58: =tblSales[[#This Row],[Quantity_sold]]*tblSales[[#This Row],[Unit_Price]] -> 2760000 | K58: =CHOOSE(RANDBETWEEN(1,3), "Cash", "Transfer", "POS") -> POS | L58: Olufemi Adewale | M58: Enugu | N58: =tblSales[[#This Row],[Unit_Price]]*tblSales[[#This Row],[Quantity_sold]]-tblSales[[#This Row],[Cost_price]]*tblSales[[#This Row],[Quantity_sold]] -> 720000
A59: SAL058 | B59: P005 | C59: =_xlfn.XLOOKUP(tblSales[[#This Row],[Product_id]],Products!A:A,Products!C:C) -> Processing Equipment | D59: CUST027 | E59: Victor Adekunle | F59: 45752 | G59: 11 | H59: =_xlfn.XLOOKUP(tblSales[[#This Row],[Product_id]],Products!A:A,Products!E:E) -> 520000 | I59: =_xlfn.XLOOKUP(tblSales[[#This Row],[Product_id]],Products!A:A,Products!F:F) -> 680000 | J59: =tblSales[[#This Row],[Quantity_sold]]*tblSales[[#This Row],[Unit_Price]] -> 7480000 | K59: =CHOOSE(RANDBETWEEN(1,3), "Cash", "Transfer", "POS") -> POS | L59: Olufemi Adewale | M59: Portharcourt | N59: =tblSales[[#This Row],[Unit_Price]]*tblSales[[#This Row],[Quantity_sold]]-tblSales[[#This Row],[Cost_price]]*tblSales[[#This Row],[Quantity_sold]] -> 1760000
A60: SAL059 | B60: P048 | C60: =_xlfn.XLOOKUP(tblSales[[#This Row],[Product_id]],Products!A:A,Products!C:C) -> Processing Equipment | D60: CUST135 | E60: Lilian Ajayi | F60: 45751 | G60: 5 | H60: =_xlfn.XLOOKUP(tblSales[[#This Row],[Product_id]],Products!A:A,Products!E:E) -> 210000 | I60: =_xlfn.XLOOKUP(tblSales[[#This Row],[Product_id]],Products!A:A,Products!F:F) -> 295000 | J60: =tblSales[[#This Row],[Quantity_sold]]*tblSales[[#This Row],[Unit_Price]] -> 1475000 | K60: =CHOOSE(RANDBETWEEN(1,3), "Cash", "Transfer", "POS") -> POS | L60: Ebele Okoro | M60: Kaduna | N60: =tblSales[[#This Row],[Unit_Price]]*tblSales[[#This Row],[Quantity_sold]]-tblSales[[#This Row],[Cost_price]]*tblSales[[#This Row],[Quantity_sold]] -> 425000
A61: SAL060 | B61: P059 | C61: =_xlfn.XLOOKUP(tblSales[[#This Row],[Product_id]],Products!A:A,Products!C:C) -> Power Equipment | D61: CUST120 | E61: Usman Bello | F61: 45749 | G61: 9 | H61: =_xlfn.XLOOKUP(tblSales[[#This Row],[Product_id]],Products!A:A,Products!E:E) -> 52000 | I61: =_xlfn.XLOOKUP(tblSales[[#This Row],[Product_id]],Products!A:A,Products!F:F) -> 78000 | J61: =tblSales[[#This Row],[Quantity_sold]]*tblSales[[#This Row],[Unit_Price]] -> 702000 | K61: =CHOOSE(RANDBETWEEN(1,3), "Cash", "Transfer", "POS") -> Cash | L61: Sadiq Bello | M61: Portharcourt | N61: =tblSales[[#This Row],[Unit_Price]]*tblSales[[#This Row],[Quantity_sold]]-tblSales[[#This Row],[Cost_price]]*tblSales[[#This Row],[Quantity_sold]] -> 234000
... A234: SAL233 | B234: P032 | C234: =_xlfn.XLOOKUP(tblSales[[#This Row],[Product_id]],Products!A:A,Products!C:C) -> Industrial Equipment | D234: CUST140 | E234: Joy Okafor | F234: 46056 | G234: 3 | H234: =_xlfn.XLOOKUP(tblSales[[#This Row],[Product_id]],Products!A:A,Products!E:E) -> 210000 | I234: =_xlfn.XLOOKUP(tblSales[[#This Row],[Product_id]],Products!A:A,Products!F:F) -> 295000 | J234: =tblSales[[#This Row],[Quantity_sold]]*tblSales[[#This Row],[Unit_Price]] -> 885000 | K234: =CHOOSE(RANDBETWEEN(1,3), "Cash", "Transfer", "POS") -> Transfer | L234: Olufemi Adewale | M234: Kaduna | N234: =tblSales[[#This Row],[Unit_Price]]*tblSales[[#This Row],[Quantity_sold]]-tblSales[[#This Row],[Cost_price]]*tblSales[[#This Row],[Quantity_sold]] -> 255000

Sheet Products
A1: Product_id | B1: Product_name | C1: Category | D1: Fabrication_date | E1: Cost_price | F1: Unit_price | G1: Quantity_produced | H1: Quantity_sold | I1: Quantity_available | J1: Fabricator | K1: Warranty | L1: Status | M1: Restocking
A2: P001 | B2: Maize Sheller | C2: Agricultural Machine | D2: 45301 | E2: 120000 | F2: 165000 | G2: 200 | H2: =SUMIFS(Sales!G:G,Sales!B:B,tblProducts[[#This Row],[Product_id]]) -> 40 | I2: =G2-H2 -> 160 | J2: Imrana Global Tech-Boom Ltd | K2: 24 | L2: =IF(I2=0,"Not Available","Available") -> Available | M2: =IF(I2<50,"Low Stock","Sufficient Stock") -> Sufficient Stock
A3: P002 | B3: Rice Thresher | C3: Agricultural Machine | D3: 45306 | E3: 180000 | F3: 245000 | G3: 180 | H3: =SUMIFS(Sales!G:G,Sales!B:B,tblProducts[[#This Row],[Product_id]]) -> 7 | I3: =G3-H3 -> 173 | J3: Imrana Global Tech-Boom Ltd | K3: 24 | L3: =IF(I3=0,"Not Available","Available") -> Available | M3: =IF(I3<50,"Low Stock","Sufficient Stock") -> Sufficient Stock
A4: P003 | B4: Groundnut Decorticator | C4: Agricultural Machine | D4: 45311 | E4: 95000 | F4: 135000 | G4: 160 | H4: =SUMIFS(Sales!G:G,Sales!B:B,tblProducts[[#This Row],[Product_id]]) -> 43 | I4: =G4-H4 -> 117 | J4: Imrana Global Tech-Boom Ltd | K4: 24 | L4: =IF(I4=0,"Not Available","Available") -> Available | M4: =IF(I4<50,"Low Stock","Sufficient Stock") -> Sufficient Stock
A5: P004 | B5: Cassava Grater | C5: Processing Equipment | D5: 45313 | E5: 210000 | F5: 290000 | G5: 60 | H5: =SUMIFS(Sales!G:G,Sales!B:B,tblProducts[[#This Row],[Product_id]]) -> 0 | I5: =G5-H5 -> 60 | J5: Imrana Global Tech-Boom Ltd | K5: 24 | L5: =IF(I5=0,"Not Available","Available") -> Available | M5: =IF(I5<50,"Low Stock","Sufficient Stock") -> Sufficient Stock
A6: P005 | B6: Palm Oil Press | C6: Processing Equipment | D6: 45323 | E6: 520000 | F6: 680000 | G6: 170 | H6: =SUMIFS(Sales!G:G,Sales!B:B,tblProducts[[#This Row],[Product_id]]) -> 11 | I6: =G6-H6 -> 159 | J6: Imrana Global Tech-Boom Ltd | K6: 24 | L6: =IF(I6=0,"Not Available","Available") -> Available | M6: =IF(I6<50,"Low Stock","Sufficient Stock") -> Sufficient Stock
A7: P006 | B7: Feed Mixer | C7: Agricultural Equipment | D7: 45327 | E7: 260000 | F7: 345000 | G7: 150 | H7: =SUMIFS(Sales!G:G,Sales!B:B,tblProducts[[#This Row],[Product_id]]) -> 19 | I7: =G7-H7 -> 131 | J7: Imrana Global Tech-Boom Ltd | K7: 24 | L7: =IF(I7=0,"Not Available","Available") -> Available | M7: =IF(I7<50,"Low Stock","Sufficient Stock") -> Sufficient Stock
A8: P007 | B8: Poultry Feeder | C8: Agricultural Equipment | D8: 45329 | E8: 18000 | F8: 28000 | G8: 80 | H8: =SUMIFS(Sales!G:G,Sales!B:B,tblProducts[[#This Row],[Product_id]]) -> 17 | I8: =G8-H8 -> 63 | J8: Imrana Global Tech-Boom Ltd | K8: 24 | L8: =IF(I8=0,"Not Available","Available") -> Available | M8: =IF(I8<50,"Low Stock","Sufficient Stock") -> Sufficient Stock
A9: P008 | B9: Poultry Drinker | C9: Agricultural Equipment | D9: 45329 | E9: 15000 | F9: 24000 | G9: 50 | H9: =SUMIFS(Sales!G:G,Sales!B:B,tblProducts[[#This Row],[Product_id]]) -> 21 | I9: =G9-H9 -> 29 | J9: Imrana Global Tech-Boom Ltd | K9: 24 | L9: =IF(I9=0,"Not Available","Available") -> Available | M9: =IF(I9<50,"Low Stock","Sufficient Stock") -> Low Stock
A10: P009 | B10: Fish Smoking Kiln | C10: Agricultural Equipment | D10: 45334 | E10: 135000 | F10: 185000 | G10: 90 | H10: =SUMIFS(Sales!G:G,Sales!B:B,tblProducts[[#This Row],[Product_id]]) -> 10 | I10: =G10-H10 -> 80 | J10: Imrana Global Tech-Boom Ltd | K10: 24 | L10: =IF(I10=0,"Not Available","Available") -> Available | M10: =IF(I10<50,"Low Stock","Sufficient Stock") -> Sufficient Stock
A11: P010 | B11: Fish Feed Pelletizer | C11: Processing Equipment | D11: 45337 | E11: 310000 | F11: 420000 | G11: 140 | H11: =SUMIFS(Sales!G:G,Sales!B:B,tblProducts[[#This Row],[Product_id]]) -> 10 | I11: =G11-H11 -> 130 | J11: Imrana Global Tech-Boom Ltd | K11: 24 | L11: =IF(I11=0,"Not Available","Available") -> Available | M11: =IF(I11<50,"Low Stock","Sufficient Stock") -> Sufficient Stock
A12: P011 | B12: Water Pump (2HP) | C12: Power Equipment | D12: 45340 | E12: 85000 | F12: 120000 | G12: 210 | H12: =SUMIFS(Sales!G:G,Sales!B:B,tblProducts[[#This Row],[Product_id]]) -> 0 | I12: =G12-H12 -> 210 | J12: Imrana Global Tech-Boom Ltd | K12: 24 | L12: =IF(I12=0,"Not Available","Available") -> Available | M12: =IF(I12<50,"Low Stock","Sufficient Stock") -> Sufficient Stock
A13: P012 | B13: Spraying Machine | C13: Agricultural Equipment | D13: 45342 | E13: 42000 | F13: 65000 | G13: 50 | H13: =SUMIFS(Sales!G:G,Sales!B:B,tblProducts[[#This Row],[Product_id]]) -> 28 | I13: =G13-H13 -> 22 | J13: Imrana Global Tech-Boom Ltd | K13: 24 | L13: =IF(I13=0,"Not Available","Available") -> Available | M13: =IF(I13<50,"Low Stock","Sufficient Stock") -> Low Stock
... A107: P106 | B107: Farm Produce Trolley | C107: Agriculture Equipment | D107: 45489 | E107: 44000 | F107: 63000 | G107: 450 | H107: =SUMIFS(Sales!G:G,Sales!B:B,tblProducts[[#This Row],[Product_id]]) -> 8 | I107: =G107-H107 -> 442 | J107: Imrana Global Tech-Boom Ltd | K107: 24 | L107: =IF(I107=0,"Not Available","Available") -> Available | M107: =IF(I107<50,"Low Stock","Sufficient Stock") -> Sufficient Stock

Sheet Customers
A1: Customer ID | B1: Customer Name | C1: Region | D1: Age | E1: Phone Number | F1: Customer Type | G1: Purchase Type
A2: CUST001 | B2: Chinedu Okafor | C2: Lagos | D2: 34 | E2: 8031234567 | F2: Retail | G2: =CHOOSE(RANDBETWEEN(1,2), "Onsite", "Online") -> Onsite
A3: CUST002 | B3: Aisha Bello | C3: Abuja | D3: 29 | E3: 8022345678 | F3: Institutional | G3: =CHOOSE(RANDBETWEEN(1,2), "Onsite", "Online") -> Onsite
A4: CUST003 | B4: Emeka Umeh | C4: Enugu | D4: 41 | E4: 8033456789 | F4: Farmer Cooperative | G4: =CHOOSE(RANDBETWEEN(1,2), "Onsite", "Online") -> Onsite
A5: CUST004 | B5: Halima Musa | C5: Kano | D5: 37 | E5: 8044567890 | F5: Retail | G5: =CHOOSE(RANDBETWEEN(1,2), "Onsite", "Online") -> Onsite
A6: CUST005 | B6: Kunle Adeyemi | C6: Ogun | D6: 45 | E6: 8055678901 | F6: Institutional | G6: =CHOOSE(RANDBETWEEN(1,2), "Onsite", "Online") -> Online
A7: CUST006 | B7: Sadiq Umar | C7: Kaduna | D7: 28 | E7: 8066789012 | F7: Retail | G7: =CHOOSE(RANDBETWEEN(1,2), "Onsite", "Online") -> Onsite
A8: CUST007 | B8: Sandra Adebayo | C8: Ibadan | D8: 32 | E8: 8077890123 | F8: Retail | G8: =CHOOSE(RANDBETWEEN(1,2), "Onsite", "Online") -> Onsite
A9: CUST008 | B9: Amara Nwosu | C9: Port Harcourt | D9: 39 | E9: 8088901234 | F9: Farmer Cooperative | G9: =CHOOSE(RANDBETWEEN(1,2), "Onsite", "Online") -> Online
A10: CUST009 | B10: Adetola Williams | C10: Lagos | D10: 51 | E10: 8099012345 | F10: Institutional | G10: =CHOOSE(RANDBETWEEN(1,2), "Onsite", "Online") -> Onsite
A11: CUST010 | B11: Fatima Abdullahi | C11: Kano | D11: 26 | E11: 8010123456 | F11: Retail | G11: =CHOOSE(RANDBETWEEN(1,2), "Onsite", "Online") -> Onsite
A12: CUST011 | B12: Oluwatobi Akinola | C12: Ibadan | D12: 30 | E12: 8021234567 | F12: Retail | G12: =CHOOSE(RANDBETWEEN(1,2), "Onsite", "Online") -> Online
A13: CUST012 | B13: Bashir Mohammed | C13: Abuja | D13: 44 | E13: 8032345678 | F13: Institutional | G13: =CHOOSE(RANDBETWEEN(1,2), "Onsite", "Online") -> Online
... A251: CUST250 | B251: Obinna Chukwu | C251: Enugu | D251: 49 | E251: 8029123482 | F251: Institutional | G251: =CHOOSE(RANDBETWEEN(1,2), "Onsite", "Online") -> Online

Sheet Calendar
A1: Date | B1: Year | C1: Month | D1: Day | E1: Quarter | F1: Weekday
A2: 45658 | B2: 2025 | C2: January | D2: 1 | E2: Q1 | F2: Wednesday
A3: 45659 | B3: 2025 | C3: January | D3: 2 | E3: Q1 | F3: Thursday
A4: 45660 | B4: 2025 | C4: January | D4: 3 | E4: Q1 | F4: Friday
A5: 45661 | B5: 2025 | C5: January | D5: 4 | E5: Q1 | F5: Saturday
A6: 45662 | B6: 2025 | C6: January | D6: 5 | E6: Q1 | F6: Sunday
A7: 45663 | B7: 2025 | C7: January | D7: 6 | E7: Q1 | F7: Monday
A8: 45664 | B8: 2025 | C8: January | D8: 7 | E8: Q1 | F8: Tuesday
A9: 45665 | B9: 2025 | C9: January | D9: 8 | E9: Q1 | F9: Wednesday
A10: 45666 | B10: 2025 | C10: January | D10: 9 | E10: Q1 | F10: Thursday
A11: 45667 | B11: 2025 | C11: January | D11: 10 | E11: Q1 | F11: Friday
A12: 45668 | B12: 2025 | C12: January | D12: 11 | E12: Q1 | F12: Saturday
A13: 45669 | B13: 2025 | C13: January | D13: 12 | E13: Q1 | F13: Sunday
... A365: 46021 | B365: 2025 | C365: December | D365: 30 | E365: Q4 | F365: Tuesday

Sheet Sales_Pivots
C1: IMRANA GLOBAL TECH-BOOM LTD (2025 Business Insights)
A5: Total Sales by Month | D5: Sales by Product Category | G5: Quantity Sold by Region | K5: Top 10 Customers
A6: Months | B6: Total Amount | D6: Category | E6: Total Amount | G6: Region | H6: Quantity Purchased | I6: Total Amount | K6: Customers | L6: Total Amount | M6: Sales by Customer
A7: Jan | B7: 65172000 | D7: Agriculture Equipment | E7: 774000 | G7: Ibadan | H7: 424 | I7: 99451500 | K7: Ahmed Ibrahim | L7: 21998500 | M7: 5
A8: Feb | B8: 82949500 | D8: Safety Equipment | E8: 3115500 | G8: Kaduna | H8: 381 | I8: 98037000 | K8: Salatu Abdullahi | L8: 19269000 | M8: 6
A9: Mar | B9: 29101000 | D9: Agricultural Structure | E9: 6830000 | G9: Enugu | H9: 367 | I9: 80336500 | K9: Farouk Bello | L9: 16775000 | M9: 3
A10: Apr | B10: 41523000 | D10: Fabrication Tools | E10: 13944000 | G10: Lagos | H10: 442 | I10: 78564500 | K10: Chika Eze | L10: 16035000 | M10: 4
A11: May | B11: 26374000 | D11: Harvesting Equipment | E11: 21840000 | G11: Portharcourt | H11: 486 | I11: 66152000 | K11: Joy Okafor | L11: 14395000 | M11: 3
A12: Jun | B12: 31958000 | D12: Energy Equipment | E12: 24700000 | G12: Kano | H12: 298 | I12: 62499000 | K12: Oluwaseun Adebayo | L12: 13750000 | M12: 4
A13: Jul | B13: 20044000 | D13: Power Equipment | E13: 35197000 | G13: Grand Total | H13: 2398 | I13: 485040500 | K13: Obinna Nwosu | L13: 12207000 | M13: 5
A14: Aug | B14: 42525000 | D14: Industrial Equipment | E14: 52446000 | K14: Kemi Olatunde | L14: 12185000 | M14: 3
A15: Sep | B15: 42907000 | D15: Agricultural Equipment | E15: 61022000 | K15: Racheal John | L15: 12172000 | M15: 4
A16: Oct | B16: 33901000 | D16: Storage Equipment | E16: 85798000 | G16: Payment_Method | H16: Sum of Total_amount | K16: Tope Okunola | L16: 11735000 | M16: 3
A17: Nov | B17: 40845000 | D17: Agricultural Machine | E17: 86180000 | G17: Cash | H17: 126087000 | K17: Grand Total | L17: 150521500 | M17: 40
A18: Dec | B18: 27741000 | D18: Processing Equipment | E18: 93194000 | G18: POS | H18: 227321500
A19: Grand Total | B19: 485040500 | D19: Grand Total | E19: 485040500 | G19: Transfer | H19: 131632000
G20: Grand Total | H20: 485040500

Sheet Sales_Dashboard
E2: IGT-B 2025 SALES PERFORMANCE DASHBOARD
F5: =SUM(Sales!J:J) -> 485040500 | H5: =COUNTA(Sales!A:A) -> 234 | K5: =AVERAGE(Sales!J:J) -> 2081718.9 | N5: =SUM(tblSales[Profit]) -> 138769000
